subprocreg/README.MD
subprocreg/__init__.py
subprocreg/requirements.txt
subprocreg/thirdparty.json
subprocreg-0.10.dist-info/LICENSE.rst
subprocreg-0.10.dist-info/METADATA
subprocreg-0.10.dist-info/WHEEL
subprocreg-0.10.dist-info/top_level.txt
subprocreg-0.10.dist-info/RECORD
