Metadata-Version: 2.1
Name: subprocreg
Version: 0.10
Summary: Execute apps using subprocess ([in]visible) + regedit.exe path search
Home-page: https://github.com/hansalemaos/subprocreg
Author: Johannes Fischer
Author-email: aulasparticularesdealemaosp@gmail.com
License: MIT
Keywords: subprocess,regedit
Classifier: Development Status :: 4 - Beta
Classifier: Programming Language :: Python :: 3 :: Only
Classifier: Programming Language :: Python :: 3.10
Classifier: Topic :: Software Development :: Libraries :: Python Modules
Classifier: Topic :: Utilities
License-File: LICENSE.rst
Requires-Dist: gracefully-kill
Requires-Dist: keyboard
Requires-Dist: reggisearch
